setup.py
nimvelo/__init__.py
nimvelo.egg-info/PKG-INFO
nimvelo.egg-info/SOURCES.txt
nimvelo.egg-info/dependency_links.txt
nimvelo.egg-info/requires.txt
nimvelo.egg-info/top_level.txt
nimvelo/stream/__init__.py