Metadata-Version: 1.1
Name: nimvelo
Version: 0.1.4
Summary: Python 2.7 client library for the Nimvelo/Sipcentric API
Home-page: https://github.com/Nimvelo/python-client
Author: David Maitland
Author-email: david.maitland@nimvelo.com
License: MIT
Keywords: nimvelo sipcentric voip pbx sms sip
Platform: UNKNOWN
Requires: math
Requires: json
Requires: logging
Requires: time
Requires: simplejson
